Workbook

Sheet Assumptions
A1: EEG field kit -- internal bill of materials, indicative costing
A2: Rev C, 1 September 2026. Companion to RFQ-EEG-001 Rev E and DSN-EEG-003 Rev D.
A3: THIS IS THE PROGRAMME'S OWN COPY AND IT CARRIES PRICES. The bidders' workbook (EEG_kit_BOM_for_bidders_RevC.xlsx) is the same part list with the prices removed and empty cells for the bidder. Do not send this file to a bidder.
A4: All unit prices are indicative single-source estimates in EUR, ex VAT and ex shipping, and are placeholders for the manufacturer's quotation. Every line records the basis it was estimated from, in the BOM sheet's last column. Yellow cells are inputs; edit those and everything recalculates.
A6: Assumption | B6: Value | C6: Note
A8: Fleet quantity scenarios (units) | C8: Quantity breaks the BOM is priced at; RFQ-EEG-001 Rev E section 10 asks bidders for these four.
A9: Scenario A -- prototypes | B9: 2
A10: Scenario B -- pilot fleet | B10: 10
A11: Scenario C -- fleet, lower bound | B11: 25
A12: Scenario D -- fleet, upper bound | B12: 50
A13: Spare assembled boards (share of fleet) | B13: 0.25 | C13: Build 25 % spares of hand-assembled units. Survives in RFQ-EEG-001 Rev E, Phase 3.
A14: EUR per USD | B14: 0.92 | C14: Used only where a supplier quotes in USD. Update on the day of the quote.
A15: Layout review NRE placeholder (EUR) | B15: 1500 | C15: RFQ-EEG-002A is a REVIEW of supplied routing, not a layout job. v1 budgeted EUR 1500 for the layout itself; the review is the cheaper half of that range, but the figure is held until the quote.
A16: Foam insert tooling placeholder (EUR) | B16: 250 | C16: One-off die or laser programme. HELD AT v1'S FIGURE AND KNOWN TO BE LOW: the CASE-00 Rev C stack is SEVEN layers, not one or two, and the layers do not share a profile -- the bays cut through different layer counts, and layer 1 of the helmet bay is 8 mm smaller all round for the halo shelf -- so this is several distinct programmes, not one. The figure is not re-estimated here because the Rev C cut file has not been drawn (PKG-EEG-015 open item 1).
A17: Stencil, fixtures and test jig placeholder (EUR) | B17: 400 | C17: JIG-EEG-009 Rev C specifies more fixtures than v1 assumed. Held at v1's figure until JIG-EEG-009 section 6.1 is quoted.
A19: Legend
A20: Yellow fill = input you can edit. Plain = formula. Prices are per unit at the stated quantity break; the manufacturer's quote replaces them.
A22: Nothing in this package has been manufactured or measured, and no price here has been quoted by a supplier. Every figure is an estimate.

Sheet BOM
A1: Item | B1: Group | C1: Description | D1: Reference part / module | E1: Qty per kit | F1: Unit EUR @2 | G1: Unit EUR @10 | H1: Unit EUR @25 | I1: Unit EUR @50 | J1: Per-kit EUR @2 | K1: Per-kit EUR @10 | L1: Per-kit EUR @25 | M1: Per-kit EUR @50 | N1: Substitutable | O1: Price basis
A3: 1 | B3: Modules | C3: ADS1299 8-channel breakout with SPI header and on-board regulators; DAISY_IN and CLKOUT accessible | D3: PIEEG-8 module | E3: 2 | F3: 95 | G3: 82 | H3: 74 | I3: 68 | J3: =$E3*F3 | K3: =$E3*G3 | L3: =$E3*H3 | M3: =$E3*I3 | N3: No (module class fixed) | O3: v1 line 3 was the bare ADS1299 at 55/48/45/42; a breakout adds its own PCB, regulators, crystal and headers. Two per kit.
A4: 2 | B4: Modules | C4: ESP32-S3 development board, 16 MB flash, 8 MB octal PSRAM | D4: Espressif ESP32-S3-DevKitC-1-N16R8 | E4: 1 | F4: 16 | G4: 14 | H4: 12.5 | I4: 11.5 | J4: =$E4*F4 | K4: =$E4*G4 | L4: =$E4*H4 | M4: =$E4*I4 | N4: No | O4: DevKitC-1-N16R8, not the bare WROOM of v1 line 15 (4.20 at the 2 break). The kit uses the DevKit's own USB and UART.
A5: 3 | B5: Modules | C5: Audio codec module with headphone amplifier, I2S | D5: ES8388 breakout | E5: 1 | F5: 9 | G5: 7.5 | H5: 6.5 | I5: 6 | J5: =$E5*F5 | K5: =$E5*G5 | L5: =$E5*H5 | M5: =$E5*I5 | N5: Yes | O5: ES8388 breakout. v1 line 11 was the bare codec at 1.60.
A6: 4 | B6: Modules | C6: USB 2.0 full-speed isolator module, >= 2.5 kV RMS | D6: ADuM4160 isolator module | E6: 1 | F6: 22 | G6: 18 | H6: 16 | I6: 15 | J6: =$E6*F6 | K6: =$E6*G6 | L6: =$E6*H6 | M6: =$E6*I6 | N6: No | O6: v1 lines 19+20 (ADuM4160 9.50 + isolated DC-DC 3.50) on a carrier board. E-24 requires the isolator from Rev A.
A7: 5 | B7: Modules | C7: Secure element breakout, I2C | D7: Adafruit ATECC608 breakout (4314) | E7: 1 | F7: 7 | G7: 6 | H7: 5.5 | I7: 5 | J7: =$E7*F7 | K7: =$E7*G7 | L7: =$E7*H7 | M7: =$E7*I7 | N7: No | O7: Adafruit ATECC608 breakout 4314. v1 line 16 was the bare part.
A8: 6 | B8: Modules | C8: Li-ion charger with power path and CE pin | D8: Adafruit bq24074 (4755) | E8: 1 | F8: 16 | G8: 14 | H8: 12.5 | I8: 11.5 | J8: =$E8*F8 | K8: =$E8*G8 | L8: =$E8*H8 | M8: =$E8*I8 | N8: Yes | O8: Adafruit bq24074 4755. v1 line 26 was the bare BQ24075.
A9: 7 | B9: Modules | C9: Battery fuel gauge, I2C | D9: Adafruit MAX17048 (5580) | E9: 1 | F9: 11 | G9: 9.5 | H9: 8.5 | I9: 8 | J9: =$E9*F9 | K9: =$E9*G9 | L9: =$E9*H9 | M9: =$E9*I9 | N9: Yes | O9: Adafruit MAX17048 5580. v1 line 27 was the bare gauge.
A10: 8 | B10: Modules | C10: Buck-boost regulator module, VSYS to 5.00 V at 1 A | D10: TPS63020 breakout | E10: 1 | F10: 13 | G10: 11 | H10: 9.5 | I10: 8.5 | J10: =$E10*F10 | K10: =$E10*G10 | L10: =$E10*H10 | M10: =$E10*I10 | N10: Yes | O10: TPS63020 breakout. NEW IN v2: package v1 had no source for the 3.3 V rail at all (ECO-EEG-016, blocking finding).
A11: 9 | B11: Modules | C11: microSD breakout, SDMMC | D11: generic microSD SDMMC breakout | E11: 1 | F11: 4 | G11: 3 | H11: 2.6 | I11: 2.3 | J11: =$E11*F11 | K11: =$E11*G11 | L11: =$E11*H11 | M11: =$E11*I11 | N11: Yes | O11: microSD SDMMC breakout. v1 line 17 was the bare socket.
A12: 10 | B12: Modules | C12: Electret microphone preamplifier module, fixed gain | D12: MAX4466 class (Adafruit 1063) | E12: 1 | F12: 8 | G12: 6.5 | H12: 5.8 | I12: 5.2 | J12: =$E12*F12 | K12: =$E12*G12 | L12: =$E12*H12 | M12: =$E12*I12 | N12: Yes | O12: MAX4466-class preamp module, Adafruit 1063 class.
A13: 11 | B13: Modules | C13: Room microphone module with hardware mute | D13: to be selected | E13: 1 | F13: 9 | G13: 7.5 | H13: 6.5 | I13: 6 | J13: =$E13*F13 | K13: =$E13*G13 | L13: =$E13*H13 | M13: =$E13*I13 | N13: Yes | O13: OPEN LINE: the room-microphone module is not selected (kit BOM note, AVL-EEG-017). Priced as a MAX4466-class board plus capsule; the figure moves when the part is chosen.
A14: 12 | B14: Modules | C14: 8-bit shift register module | D14: 74HC595 breakout | E14: 1 | F14: 4.5 | G14: 3.5 | H14: 3 | I14: 2.6 | J14: =$E14*F14 | K14: =$E14*G14 | L14: =$E14*H14 | M14: =$E14*I14 | N14: Yes | O14: 74HC595 breakout. NEW IN v2: in v1 the eight contact-light lines had nothing driving them (ECO-EEG-016).
... A49: 47 | B49: Service | C49: Provisioning, firmware load and TST-EEG-004 Rev C | D49: per TST-EEG-004 | E49: 1 | F49: 45 | G49: 25 | H49: 18 | I49: 15 | J49: =$E49*F49 | K49: =$E49*G49 | L49: =$E49*H49 | M49: =$E49*I49 | N49: n/a | O49: v1 line 54, unchanged. TST-EEG-004 Rev C is 31 steps; the figure is held until a unit has actually been through them.
C51: Total per complete kit (materials + assembly + test) | J51: =SUM(J2:J49) | K51: =SUM(K2:K49) | L51: =SUM(L2:L49) | M51: =SUM(M2:M49)
C53: Prices are indicative estimates for the manufacturer's quote to replace. Unit columns are per-unit prices at 2 / 10 / 25 / 50 kits; per-kit columns multiply by the quantity in this kit. Lines 25 and 26 are qty 0 per kit (HM-09 is one per site, FIT-01 one per build batch), so they cost nothing per kit and are priced here only so the figure exists when it is ordered.

Sheet Kit summary
A1: Cost roll-up by subsystem and scenario
A2: Every cell is a formula over the BOM sheet, rows 2 to 49. Change a price there and this sheet follows.
A4: Subsystem | B4: Per kit @2 | C4: Per kit @10 | D4: Per kit @25 | E4: Per kit @50
A6: Modules | B6: =SUMIF(BOM!$B$2:$B$49,$A6,BOM!J$2:J$49) | C6: =SUMIF(BOM!$B$2:$B$49,$A6,BOM!K$2:K$49) | D6: =SUMIF(BOM!$B$2:$B$49,$A6,BOM!L$2:L$49) | E6: =SUMIF(BOM!$B$2:$B$49,$A6,BOM!M$2:M$49)
A7: Carrier | B7: =SUMIF(BOM!$B$2:$B$49,$A7,BOM!J$2:J$49) | C7: =SUMIF(BOM!$B$2:$B$49,$A7,BOM!K$2:K$49) | D7: =SUMIF(BOM!$B$2:$B$49,$A7,BOM!L$2:L$49) | E7: =SUMIF(BOM!$B$2:$B$49,$A7,BOM!M$2:M$49)
A8: Printed | B8: =SUMIF(BOM!$B$2:$B$49,$A8,BOM!J$2:J$49) | C8: =SUMIF(BOM!$B$2:$B$49,$A8,BOM!K$2:K$49) | D8: =SUMIF(BOM!$B$2:$B$49,$A8,BOM!L$2:L$49) | E8: =SUMIF(BOM!$B$2:$B$49,$A8,BOM!M$2:M$49)
A9: Bought-in mechanical | B9: =SUMIF(BOM!$B$2:$B$49,$A9,BOM!J$2:J$49) | C9: =SUMIF(BOM!$B$2:$B$49,$A9,BOM!K$2:K$49) | D9: =SUMIF(BOM!$B$2:$B$49,$A9,BOM!L$2:L$49) | E9: =SUMIF(BOM!$B$2:$B$49,$A9,BOM!M$2:M$49)
A10: Electrodes | B10: =SUMIF(BOM!$B$2:$B$49,$A10,BOM!J$2:J$49) | C10: =SUMIF(BOM!$B$2:$B$49,$A10,BOM!K$2:K$49) | D10: =SUMIF(BOM!$B$2:$B$49,$A10,BOM!L$2:L$49) | E10: =SUMIF(BOM!$B$2:$B$49,$A10,BOM!M$2:M$49)
A11: Audio | B11: =SUMIF(BOM!$B$2:$B$49,$A11,BOM!J$2:J$49) | C11: =SUMIF(BOM!$B$2:$B$49,$A11,BOM!K$2:K$49) | D11: =SUMIF(BOM!$B$2:$B$49,$A11,BOM!L$2:L$49) | E11: =SUMIF(BOM!$B$2:$B$49,$A11,BOM!M$2:M$49)
A12: Consumables | B12: =SUMIF(BOM!$B$2:$B$49,$A12,BOM!J$2:J$49) | C12: =SUMIF(BOM!$B$2:$B$49,$A12,BOM!K$2:K$49) | D12: =SUMIF(BOM!$B$2:$B$49,$A12,BOM!L$2:L$49) | E12: =SUMIF(BOM!$B$2:$B$49,$A12,BOM!M$2:M$49)
A13: Cables | B13: =SUMIF(BOM!$B$2:$B$49,$A13,BOM!J$2:J$49) | C13: =SUMIF(BOM!$B$2:$B$49,$A13,BOM!K$2:K$49) | D13: =SUMIF(BOM!$B$2:$B$49,$A13,BOM!L$2:L$49) | E13: =SUMIF(BOM!$B$2:$B$49,$A13,BOM!M$2:M$49)
A14: Case | B14: =SUMIF(BOM!$B$2:$B$49,$A14,BOM!J$2:J$49) | C14: =SUMIF(BOM!$B$2:$B$49,$A14,BOM!K$2:K$49) | D14: =SUMIF(BOM!$B$2:$B$49,$A14,BOM!L$2:L$49) | E14: =SUMIF(BOM!$B$2:$B$49,$A14,BOM!M$2:M$49)
A15: Service | B15: =SUMIF(BOM!$B$2:$B$49,$A15,BOM!J$2:J$49) | C15: =SUMIF(BOM!$B$2:$B$49,$A15,BOM!K$2:K$49) | D15: =SUMIF(BOM!$B$2:$B$49,$A15,BOM!L$2:L$49) | E15: =SUMIF(BOM!$B$2:$B$49,$A15,BOM!M$2:M$49)
A16: Total per kit | B16: =SUM(B6:B15) | C16: =SUM(C6:C15) | D16: =SUM(D6:D15) | E16: =SUM(E6:E15)
A17: Electronics only (Modules + Carrier) | B17: =B6+B7 | C17: =C6+C7 | D17: =D6+D7 | E17: =E6+E7
A19: Programme build-up by scenario
A20: Line | B20: @2 | C20: @10 | D20: @25 | E20: @50
A22: Kits built | B22: 2 | C22: 10 | D22: 25 | E22: 50
A23: Kit cost x quantity | B23: =B16*B22 | C23: =C16*C22 | D23: =D16*D22 | E23: =E16*E22
A24: Spare assembled carriers (25% of fleet, carrier lines only) | B24: =ROUND(B22*0.25,0)*SUMIF(BOM!$B$2:$B$49,"Carrier",BOM!J$2:J$49) | C24: =ROUND(C22*0.25,0)*SUMIF(BOM!$B$2:$B$49,"Carrier",BOM!K$2:K$49) | D24: =ROUND(D22*0.25,0)*SUMIF(BOM!$B$2:$B$49,"Carrier",BOM!L$2:L$49) | E24: =ROUND(E22*0.25,0)*SUMIF(BOM!$B$2:$B$49,"Carrier",BOM!M$2:M$49)
A25: Layout review NRE | B25: 1500 | C25: 1500 | D25: 1500 | E25: 1500
A26: Foam insert tooling | B26: 250 | C26: 250 | D26: 250 | E26: 250
A27: Stencil, fixtures and test jig | B27: 400 | C27: 400 | D27: 400 | E27: 400
A28: Programme total | B28: =B23+B24+B25+B26+B27 | C28: =C23+C24+C25+C26+C27 | D28: =D23+D24+D25+D26+D27 | E28: =E23+E24+E25+E26+E27
A30: The one-off lines are placeholders from the Assumptions sheet, not quotes. The spare-carrier line prices spare BOARDS, not spare kits: a spare kit would need electrodes, a case and a helmet as well.
A32: What package v1 estimated, for comparison
A33: Line | B33: @2 | C33: @10 | D33: @25 | E33: @50
A35: v1 per-kit total (EEG_kit_BOM_INTERNAL_costed.xlsx) | B35: 740.13 | C35: 598.6 | D35: 523.32 | E35: 474.95
A36: v2 per-kit total, this sheet | B36: =B16 | C36: =C16 | D36: =D16 | E36: =E16
A37: Increase | B37: =B36-B35 | C37: =C36-C35 | D37: =D36-D35 | E37: =E36-E35
A38: Increase, per cent | B38: =ROUND((B36/B35-1)*100,0) | C38: =ROUND((C36/C35-1)*100,0) | D38: =ROUND((D36/D35-1)*100,0) | E38: =ROUND((E36/E35-1)*100,0)
A40: A v2 kit costs materially more than package v1 estimated, and the reason is the architecture rather than inflation. v2 buys MODULES where v1 bought bare silicon (DSN-EEG-003 section 2): no fine-pitch rework, no ADS1299 lead time, no BGA, but a module carries its own PCB, regulators and headers and costs several times the chip inside it. The carrier also went to four layers at 150.0 x 130.0 mm, the case and its foam insert went up several sizes PAST M-05 to hold the assembled helmet (PKG-EEG-015 section 3.2, CN-PKG-03), and MP-01, HM-02, the TPS63020 buck-boost, the 74HC595 driver and the second harness WH-02 are all new lines that v1 did not carry -- three of them because v1 had defects that made the kit unbuildable. Some lines went DOWN: ten electrode cups instead of twelve, and three DIN sockets instead of fifteen.
